{
  "type": "FeatureCollection",
  "features": [
    {
      "type": "Feature",
      "geometry": {
        "type": "Point",
        "coordinates": [
          null,
          null
        ]
      },
      "properties": {
        "id": "prefecture-97302-01",
        "codeInsee": "97302",
        "dateMiseAJour": "2013-10-02",
        "pivotLocal": "prefecture",
        "Nom": "Préfecture - Guyane",
        "EditeurSource": "La Direction de l'information légale et administrative (Premier ministre)",
        "Adresse": {
          "type": "géopostale",
          "Ligne": [
            "BP 7008",
            "Rue Fiedmond"
          ],
          "CodePostal": "97307",
          "NomCommune": "Cayenne Cedex"
        },
        "CoordonnéesNum": {
          "Téléphone": "+594 594 39 45 00",
          "Télécopie": "+594 594 30 02 77",
          "Email": "courrier@guyane.pref.gouv.fr",
          "Url": "http://www.guyane.pref.gouv.fr"
        },
        "Ouverture": {
          "PlageJ": {
            "début": "lundi",
            "fin": "vendredi",
            "PlageH": {
              "début": "07:30:00",
              "fin": "12:30:00"
            }
          }
        }
      }
    }
  ]
}