{
  "type": "FeatureCollection",
  "features": [
    {
      "type": "Feature",
      "geometry": {
        "type": "Point",
        "coordinates": [
          0.271986,
          45.680168
        ]
      },
      "properties": {
        "Organisme": {
          "id": "afpa-16232-01",
          "codeInsee": "16232",
          "dateMiseAJour": "2016-09-08",
          "pivotLocal": "afpa",
          "Nom": "Agence nationale pour la formation professionnelle des adultes (Afpa) - Centre d'Angoulême",
          "EditeurSource": "La Direction de l'information légale et administrative (Premier ministre)",
          "Adresse": {
            "type": "géopostale",
            "Ligne": "104 route du Lac-Mélot",
            "CodePostal": "16600",
            "NomCommune": "Mornac",
            "Localisation": {
              "Latitude": "45.680168",
              "Longitude": "0.271986",
              "Précision": "8"
            },
            "Accessibilité": {
              "type": "ACC"
            }
          },
          "CoordonnéesNum": {
            "Téléphone": {
              "coût": "Numéro violet ou majoré.",
              "$t": "3936"
            },
            "Url": "http://www.afpa.fr"
          }
        }
      }
    },
    {
      "type": "Feature",
      "geometry": {
        "type": "Point",
        "coordinates": [
          -0.2579814,
          45.6831631
        ]
      },
      "properties": {
        "Organisme": {
          "id": "afpa-16304-01",
          "codeInsee": "16304",
          "dateMiseAJour": "2014-09-02",
          "pivotLocal": "afpa",
          "Nom": "Agence nationale pour la formation professionnelle des adultes (Afpa) - Centre de Saint-Brice",
          "EditeurSource": "La Direction de l'information légale et administrative (Premier ministre)",
          "Adresse": {
            "type": "géopostale",
            "Ligne": "44, rue de la Maurie",
            "CodePostal": "16100",
            "NomCommune": "Saint-Brice",
            "Localisation": {
              "Latitude": "45.6831631",
              "Longitude": "-0.2579814",
              "Précision": "8"
            }
          },
          "CoordonnéesNum": {
            "Téléphone": {
              "coût": "Numéro violet ou majoré. Écoutez le tarif en début d'appel.",
              "$t": "3936"
            },
            "Url": "http://www.poitou-charentes.afpa.fr"
          }
        }
      }
    },
    {
      "type": "Feature",
      "geometry": {
        "type": "Point",
        "coordinates": [
          0.1161356,
          45.6480334
        ]
      },
      "properties": {
        "Organisme": {
          "id": "afpa-16015-01",
          "codeInsee": "16015",
          "dateMiseAJour": "2014-09-02",
          "pivotLocal": "afpa",
          "Nom": "Agence nationale pour la formation professionnelle des adultes (Afpa) - Centre d'Angoulême - Basseau",
          "EditeurSource": "La Direction de l'information légale et administrative (Premier ministre)",
          "Adresse": {
            "type": "géopostale",
            "Ligne": "Rue Saint-Vincent-de-Paul",
            "CodePostal": "16000",
            "NomCommune": "Angoulême",
            "Localisation": {
              "Latitude": "45.6480334",
              "Longitude": "0.1161356",
              "Précision": "8"
            }
          },
          "CoordonnéesNum": {
            "Téléphone": {
              "coût": "Numéro violet ou majoré. Écoutez le tarif en début d'appel.",
              "$t": "3936"
            },
            "Url": "http://www.poitou-charentes.afpa.fr"
          }
        }
      }
    }
  ]
}