{
  "type": "FeatureCollection",
  "features": [
    {
      "type": "Feature",
      "geometry": {
        "type": "Point",
        "coordinates": [
          -1.0320221,
          45.9347381
        ]
      },
      "properties": {
        "id": "afpa-17299-03",
        "codeInsee": "17299",
        "dateMiseAJour": "2017-10-02",
        "pivotLocal": "afpa",
        "Nom": "Agence nationale pour la formation professionnelle des adultes (Afpa) - Centre de Rochefort - La Pérouse",
        "EditeurSource": "La Direction de l'information légale et administrative (Premier ministre)",
        "Adresse": {
          "type": "géopostale",
          "Ligne": "Port de Plaisance",
          "CodePostal": "17300",
          "NomCommune": "Rochefort",
          "Localisation": {
            "Latitude": "45.9347381",
            "Longitude": "-1.0320221",
            "Précision": "8"
          }
        },
        "CoordonnéesNum": {
          "Téléphone": {
            "coût": "Numéro violet : service payant + prix appel (dépend de votre opérateur, pour connaître le tarif écoutez le message en début d’appel).",
            "$t": "3936"
          },
          "Url": "https://www.afpa.fr"
        },
        "Commentaire": "Contacter l'accueil pour connaitre les horaires d'ouverture."
      }
    },
    {
      "type": "Feature",
      "geometry": {
        "type": "Point",
        "coordinates": [
          -0.952493,
          45.930673
        ]
      },
      "properties": {
        "id": "afpa-17299-02",
        "codeInsee": "17299",
        "dateMiseAJour": "2017-10-02",
        "pivotLocal": "afpa",
        "Nom": "Agence nationale pour la formation professionnelle des adultes (Afpa) - Centre de Rochefort - Arsenal",
        "EditeurSource": "La Direction de l'information légale et administrative (Premier ministre)",
        "Adresse": {
          "type": "géopostale",
          "Ligne": "Rue Auguste-Giral",
          "CodePostal": "17300",
          "NomCommune": "Rochefort",
          "Localisation": {
            "Latitude": "45.930673",
            "Longitude": "-0.952493",
            "Précision": "8"
          }
        },
        "CoordonnéesNum": {
          "Téléphone": {
            "coût": "Numéro violet : service payant + prix appel (dépend de votre opérateur, pour connaître le tarif écoutez le message en début d’appel).",
            "$t": "3936"
          },
          "Url": "https://www.afpa.fr"
        },
        "Commentaire": "Contacter l'accueil pour connaitre les horaires d’ouverture."
      }
    },
    {
      "type": "Feature",
      "geometry": {
        "type": "Point",
        "coordinates": [
          -0.963983,
          45.958496
        ]
      },
      "properties": {
        "id": "afpa-17299-01",
        "codeInsee": "17299",
        "dateMiseAJour": "2017-10-02",
        "pivotLocal": "afpa",
        "Nom": "Agence nationale pour la formation professionnelle des adultes (Afpa) - Centre de Rochefort",
        "EditeurSource": "La Direction de l'information légale et administrative (Premier ministre)",
        "Adresse": {
          "type": "géopostale",
          "Ligne": "57 avenue Bernadotte",
          "CodePostal": "17300",
          "NomCommune": "Rochefort",
          "Localisation": {
            "Latitude": "45.958496",
            "Longitude": "-0.963983",
            "Précision": "8"
          }
        },
        "CoordonnéesNum": {
          "Téléphone": {
            "coût": "Numéro violet : service payant + prix appel (dépend de votre opérateur, pour connaître le tarif écoutez le message en début d’appel).",
            "$t": "3936"
          },
          "Url": "https://www.afpa.fr"
        },
        "Commentaire": "Contacter l'accueil pour connaitre les horaires d'ouverture."
      }
    }
  ]
}