{
  "type": "FeatureCollection",
  "features": [
    {
      "type": "Feature",
      "geometry": {
        "type": "Point",
        "coordinates": [
          6.2216221,
          48.7059349
        ]
      },
      "properties": {
        "codeInsee": "54184",
        "dateMiseAJour": "2017-03-09",
        "id": "permanence_juridique-54184-01",
        "idPresta": "4cac9e5f293594648a00030a",
        "pivotLocal": "permanence_juridique",
        "Nom": "Point d'accès au droit d'Essey-Lès-Nancy",
        "EditeurSource": "Direction de l’information légale et administrative",
        "Adresse": {
          "type": "géopostale",
          "Ligne": [
            "Maison des Associations",
            "2 rue des Basses ruelles"
          ],
          "CodePostal": "54270",
          "NomCommune": "ESSEY LES NANCY",
          "Localisation": {
            "Latitude": "48.7059349",
            "Longitude": "6.2216221",
            "Précision": "8"
          }
        },
        "CoordonnéesNum": {
          "Téléphone": "+33 3 83 33 44 38",
          "Sve": "http://www.justice.gouv.fr/sve"
        }
      }
    },
    {
      "type": "Feature",
      "geometry": {
        "type": "Point",
        "coordinates": [
          5.7858137,
          49.5440111
        ]
      },
      "properties": {
        "codeInsee": "54382",
        "dateMiseAJour": "2017-03-09",
        "id": "permanence_juridique-54382-01",
        "idPresta": "4cac9e5f293594648a00030f",
        "pivotLocal": "permanence_juridique",
        "Nom": "Point d'accès au droit de Mont-Saint-Martin",
        "EditeurSource": "Direction de l’information légale et administrative",
        "Adresse": {
          "type": "géopostale",
          "Ligne": [
            "Mairie",
            "boulevard du 8 mai 1945"
          ],
          "CodePostal": "54350",
          "NomCommune": "MONT ST MARTIN",
          "Localisation": {
            "Latitude": "49.5440111",
            "Longitude": "5.7858137",
            "Précision": "6"
          }
        },
        "CoordonnéesNum": {
          "Téléphone": "+33 3 82 25 23 70",
          "Sve": "http://www.justice.gouv.fr/sve"
        }
      }
    },
    {
      "type": "Feature",
      "geometry": {
        "type": "Point",
        "coordinates": [
          6.1950679,
          48.6534327
        ]
      },
      "properties": {
        "codeInsee": "54257",
        "dateMiseAJour": "2017-03-09",
        "id": "permanence_juridique-54257-01",
        "idPresta": "4cac9e5f293594648a00030b",
        "pivotLocal": "permanence_juridique",
        "Nom": "Point d'accès au droit de Heillecourt",
        "EditeurSource": "Direction de l’information légale et administrative",
        "Adresse": {
          "type": "géopostale",
          "Ligne": [
            "Mairie",
            "58 Grande rue"
          ],
          "CodePostal": "54180",
          "NomCommune": "HEILLECOURT",
          "Localisation": {
            "Latitude": "48.6534327",
            "Longitude": "6.1950679",
            "Précision": "8"
          }
        },
        "CoordonnéesNum": {
          "Téléphone": "+33 3 83 55 17 20",
          "Sve": "http://www.justice.gouv.fr/sve"
        }
      }
    },
    {
      "type": "Feature",
      "geometry": {
        "type": "Point",
        "coordinates": [
          6.1610742,
          48.6229147
        ]
      },
      "properties": {
        "codeInsee": "54328",
        "dateMiseAJour": "2017-03-09",
        "id": "permanence_juridique-54328-01",
        "idPresta": "4cac9e5f293594648a00030d",
        "pivotLocal": "permanence_juridique",
        "Nom": "Point d'accès au droit de Ludres",
        "EditeurSource": "Direction de l’information légale et administrative",
        "Adresse": {
          "type": "géopostale",
          "Ligne": [
            "Mairie",
            "place Ferri de Ludres"
          ],
          "CodePostal": "54710",
          "NomCommune": "LUDRES",
          "Localisation": {
            "Latitude": "48.6229147",
            "Longitude": "6.1610742",
            "Précision": "4"
          }
        },
        "CoordonnéesNum": {
          "Téléphone": "+33 3 83 26 14 33",
          "Sve": "http://www.justice.gouv.fr/sve"
        }
      }
    },
    {
      "type": "Feature",
      "geometry": {
        "type": "Point",
        "coordinates": [
          6.2067822,
          48.7002071
        ]
      },
      "properties": {
        "codeInsee": "54482",
        "dateMiseAJour": "2017-03-09",
        "id": "permanence_juridique-54482-01",
        "idPresta": "4cac9e5f293594648a000316",
        "pivotLocal": "permanence_juridique",
        "Nom": "Point d'accès au droit de Saint-Max",
        "EditeurSource": "Direction de l’information légale et administrative",
        "Adresse": {
          "type": "géopostale",
          "Ligne": [
            "Mairie",
            "32 avenue Carnot"
          ],
          "CodePostal": "54130",
          "NomCommune": "ST MAX",
          "Localisation": {
            "Latitude": "48.7002071",
            "Longitude": "6.2067822",
            "Précision": "8"
          }
        },
        "CoordonnéesNum": {
          "Téléphone": "+33 3 83 18 32 32",
          "Sve": "http://www.justice.gouv.fr/sve"
        }
      }
    },
    {
      "type": "Feature",
      "geometry": {
        "type": "Point",
        "coordinates": [
          6.2579132,
          48.6979353
        ]
      },
      "properties": {
        "codeInsee": "54439",
        "dateMiseAJour": "2017-03-09",
        "id": "permanence_juridique-54439-01",
        "idPresta": "4cac9e5f293594648a000315",
        "pivotLocal": "permanence_juridique",
        "Nom": "Point d'accès au droit de Pulnoy",
        "EditeurSource": "Direction de l’information légale et administrative",
        "Adresse": {
          "type": "géopostale",
          "Ligne": [
            "Mairie",
            "2 chemin du Tir"
          ],
          "CodePostal": "54425",
          "NomCommune": "PULNOY",
          "Localisation": {
            "Latitude": "48.6979353",
            "Longitude": "6.2579132",
            "Précision": "6"
          }
        },
        "CoordonnéesNum": {
          "Téléphone": "+33 3 83 29 14 33",
          "Sve": "http://www.justice.gouv.fr/sve"
        }
      }
    }
  ]
}